{
    "env": "prod",
    "url": "https://www.maisonscompere.be",
    "cache": true,
    "user": "root",
    "group": "www-data",
    "theme": "maisonscompere_theme",
    "app_writable_folder": [
        "eww",
        "languages"
    ],
    "add_script": "scripts/install_uploads.sh",
    "plugins": 
            [
                "acf-content-analysis-for-yoast-seo", 
                "acf-flexible-content-modal", 
                "advanced-custom-fields-font-awesome", 
                "advanced-custom-fields-pro", 
                "amp", 
                "autoptimize",
                "contact-form-7",
                "breadcrumb-navxt", 
                "classic-editor", 
                "cookie-notice", 
                "duplicate-post",
                "flamingo",
                "ewww-image-optimizer",
                "redirection",
                "simple-share-buttons-adder", 
                "wpml-media-translation", 
                "wpml-multilingual-cms", 
                "wpml-string-translation", 
                "wordpress-seo",
                "cache-enabler",
                "cdn-enabler"
            ]
}
